{"summaries":[{"symbol":{"__symbol":0},"metadata":{"__symbolic":"class"},"type":{"summaryKind":3,"type":{"reference":{"__symbol":0},"diDeps":[{"isAttribute":false,"isHost":false,"isSelf":false,"isSkipSelf":false,"isOptional":false,"token":{"identifier":{"reference":{"__symbol":1}}}},{"isAttribute":false,"isHost":false,"isSelf":false,"isSkipSelf":false,"isOptional":false,"token":{"identifier":{"reference":{"__symbol":2}}}},{"isAttribute":false,"isHost":false,"isSelf":false,"isSkipSelf":false,"isOptional":false,"token":{"identifier":{"reference":{"__symbol":3}}}},{"isAttribute":false,"isHost":false,"isSelf":false,"isSkipSelf":false,"isOptional":false,"token":{"identifier":{"reference":{"__symbol":4}}}}],"lifecycleHooks":[]}}}],"symbols":[{"__symbol":0,"name":"UserAuthEffects","filePath":"/Users/rawat/Documents/pankaj/angular2apps/travel-app/src/app/effects/user-auth.effect.d.ts"},{"__symbol":1,"name":"Actions","filePath":"/Users/rawat/Documents/pankaj/angular2apps/travel-app/node_modules/@ngrx/effects/src/actions.d.ts"},{"__symbol":2,"name":"UserAuthService","filePath":"/Users/rawat/Documents/pankaj/angular2apps/travel-app/src/app/services/user-auth.service.d.ts"},{"__symbol":3,"name":"ServerAuthService","filePath":"/Users/rawat/Documents/pankaj/angular2apps/travel-app/src/app/services/server-auth.service.d.ts"},{"__symbol":4,"name":"Store","filePath":"/Users/rawat/Documents/pankaj/angular2apps/travel-app/node_modules/@ngrx/store/src/store.d.ts"}]}